brevisurl/__init__.py
brevisurl/context_processors.py
brevisurl/models.py
brevisurl/settings.py
brevisurl/urls.py
brevisurl/utils.py
brevisurl/views.py
brevisurl/backends/__init__.py
brevisurl/backends/base.py
brevisurl/backends/local.py
brevisurl/migrations/0001_initial.py
brevisurl/migrations/0002_auto__add_index_shorturl_original_url.py
brevisurl/migrations/__init__.py
brevisurl/templatetags/__init__.py
brevisurl/templatetags/brevisurltags.py
brevisurl/tests/__init__.py
brevisurl/tests/test_brevisurl.py
brevisurl/tests/test_context_processors.py
brevisurl/tests/test_models.py
brevisurl/tests/test_utils.py
brevisurl/tests/test_views.py
brevisurl/tests/backends/__init__.py
brevisurl/tests/backends/test_local.py
brevisurl/tests/templatetags/__init__.py
brevisurl/tests/templatetags/test_brevisurltags.py
django_brevisurl-2.0.2.dist-info/DESCRIPTION.rst
django_brevisurl-2.0.2.dist-info/METADATA
django_brevisurl-2.0.2.dist-info/metadata.json
django_brevisurl-2.0.2.dist-info/RECORD
django_brevisurl-2.0.2.dist-info/top_level.txt
django_brevisurl-2.0.2.dist-info/WHEEL
