Metadata-Version: 2.0
Name: django-brevisurl
Version: 2.0.2
Summary: django-brevisurl is django app for shortening urls
Home-page: http://www.codescale.net/en/community#django-brevisurl
Author: Vladimír Gorej
Author-email: gorej@codescale.net
License: BSD
Download-URL: http://github.com/char0n/django-brevisurl/tarball/master
Keywords: url short shortener
Platform: any
Classifier: Development Status :: 5 - Production/Stable
Classifier: Environment :: Web Environment
Classifier: Intended Audience :: Developers
Classifier: Intended Audience :: Information Technology
Classifier: License :: OSI Approved :: BSD License
Classifier: Operating System :: OS Independent
Classifier: Programming Language :: Python
Classifier: Topic :: Utilities
Classifier: Topic :: Internet :: WWW/HTTP
Requires-Dist: django
Requires-Dist: south
